flet_core/__init__.py
flet_core/adaptive_control.py
flet_core/alert_dialog.py
flet_core/alignment.py
flet_core/animated_switcher.py
flet_core/animation.py
flet_core/app_bar.py
flet_core/audio.py
flet_core/audio_recorder.py
flet_core/auto_complete.py
flet_core/autofill_group.py
flet_core/badge.py
flet_core/banner.py
flet_core/blur.py
flet_core/border.py
flet_core/border_radius.py
flet_core/bottom_app_bar.py
flet_core/bottom_sheet.py
flet_core/buttons.py
flet_core/canvas/__init__.py
flet_core/canvas/arc.py
flet_core/canvas/canvas.py
flet_core/canvas/circle.py
flet_core/canvas/color.py
flet_core/canvas/fill.py
flet_core/canvas/line.py
flet_core/canvas/oval.py
flet_core/canvas/path.py
flet_core/canvas/points.py
flet_core/canvas/rect.py
flet_core/canvas/shadow.py
flet_core/canvas/shape.py
flet_core/canvas/text.py
flet_core/card.py
flet_core/card_swiper.py
flet_core/charts/bar_chart.py
flet_core/charts/bar_chart_group.py
flet_core/charts/bar_chart_rod.py
flet_core/charts/bar_chart_rod_stack_item.py
flet_core/charts/chart_axis.py
flet_core/charts/chart_axis_label.py
flet_core/charts/chart_grid_lines.py
flet_core/charts/chart_point_line.py
flet_core/charts/chart_point_shape.py
flet_core/charts/line_chart.py
flet_core/charts/line_chart_data.py
flet_core/charts/line_chart_data_point.py
flet_core/charts/pie_chart.py
flet_core/charts/pie_chart_section.py
flet_core/checkbox.py
flet_core/chip.py
flet_core/circle_avatar.py
flet_core/client_storage.py
flet_core/colors.py
flet_core/column.py
flet_core/connection.py
flet_core/constrained_control.py
flet_core/container.py
flet_core/control.py
flet_core/control_event.py
flet_core/cupertino_action_sheet.py
flet_core/cupertino_action_sheet_action.py
flet_core/cupertino_activity_indicator.py
flet_core/cupertino_alert_dialog.py
flet_core/cupertino_app_bar.py
flet_core/cupertino_bottom_sheet.py
flet_core/cupertino_button.py
flet_core/cupertino_checkbox.py
flet_core/cupertino_colors.py
flet_core/cupertino_context_menu.py
flet_contrib_core-2024.12.7.2153.dist-info/METADATA
flet_contrib_core-2024.12.7.2153.dist-info/WHEEL
flet_contrib_core-2024.12.7.2153.dist-info/RECORD
